music_bg_extra/__init__.py
music_bg_extra/processors/blur.py
music_bg_extra/processors/circle.py
music_bg_extra/processors/gradients.py
music_bg_extra/processors/pop.py
music_bg_extra/processors/print.py
music_bg_extra/utils.py
music_bg_extra/variables/colors.py
music_bg_extra/variables/uuid_gen.py
music_bg_extra-0.2.6.dist-info/entry_points.txt
music_bg_extra-0.2.6.dist-info/WHEEL
music_bg_extra-0.2.6.dist-info/METADATA
music_bg_extra-0.2.6.dist-info/RECORD
