Metadata-Version: 2.1
Name: music-bg-extra
Version: 0.2.6
Summary: Extra utils for music_bg
Home-page: https://github.com/music-bg/music_bg_extra
Keywords: Music,Image Processing,Music Background
Author: Pavel Kirilin
Author-email: win10@list.ru
Requires-Python: >=3.8,<3.11
Classifier: Programming Language :: Python :: 3
Classifier: Programming Language :: Python :: 3.8
Classifier: Programming Language :: Python :: 3.9
Classifier: Topic :: Multimedia :: Sound/Audio
Classifier: Topic :: Scientific/Engineering :: Image Processing
Classifier: Typing :: Typed
Requires-Dist: Pillow-SIMD (>=7.0.0,<8.0.0)
Requires-Dist: music-bg (>=0.2.0,<0.3.0)
Requires-Dist: numpy (>=1.21.2,<2.0.0)
Project-URL: Documentation, https://github.com/music-bg/music_bg/wiki
Project-URL: Repository, https://github.com/music-bg/music_bg_extra
